{
    "google": [
        {
            "operator": "site",
            "description": "Restricts the search to results from a specific website or domain.",
            "example": "site:github.com \"tensorflow\""
        },
        {
            "operator": "intitle",
            "description": "Searches for a specific word or phrase in the title of web pages.",
            "example": "intitle:\"machine learning\" \"tutorial\""
        },
        {
            "operator": "inurl",
            "description": "Looks for pages where a particular word or phrase is part of the URL.",
            "example": "inurl:admin \"login page\""
        },
        {
            "operator": "intext",
            "description": "Searches for keywords or phrases within the body text of a webpage.",
            "example": "intext:\"open source project\" \"JavaScript\""
        },
        {
            "operator": "-site",
            "description": "Excludes a specific site or domain from the search results.",
            "example": "\"how to use TensorFlow\" -site:youtube.com"
        },
        {
            "operator": "-intitle",
            "description": "Excludes pages with specific words in their title.",
            "example": "machine learning -intitle:\"beginner\""
        },
        {
            "operator": "-inurl",
            "description": "Excludes results with certain keywords in the URL.",
            "example": "deep learning -inurl:blog"
        },
        {
            "operator": "-intext",
            "description": "Excludes pages that contain certain text within their body.",
            "example": "\"data science\" -intext:\"advertisement\""
        }
    ]
}
