{
  "http://blob.core.usgovcloudapi.net": {
    "js": 1
  },
  "https://1bremertonwa.blob.core.usgovcloudapi.net": {
    "pdf": 2
  },
  "https://1governorny.blob.core.usgovcloudapi.net": {
    "net/": 1
  },
  "https://1osbar.blob.core.usgovcloudapi.net": {
    "pdf": 8,
    "txt": 1
  },
  "https://1sacramentocapd.blob.core.usgovcloudapi.net": {
    "pdf": 7
  },
  "https://1sandiegocountyso.blob.core.usgovcloudapi.net": {
    "net/": 1
  },
  "https://1sanfranciscopd.blob.core.usgovcloudapi.net": {
    "txt": 1,
    "pdf": 35,
    "xlsx": 14,
    "wav": 3,
    "zip": 1,
    "mp4": 9,
    "doc": 2
  },
  "https://1spokanecountywa.blob.core.usgovcloudapi.net": {
    "pdf": 2,
    "docx": 1
  },
  "https://1susd.blob.core.usgovcloudapi.net": {
    "mp4": 2
  },
  "https://1tumwaterwa.blob.core.usgovcloudapi.net": {
    "ico": 1,
    "jpg": 1,
    "jpeg": 1
  },
  "https://a067dqmpublic.blob.core.usgovcloudapi.net": {
    "pdf": 14
  },
  "https://afcweb.blob.core.usgovcloudapi.net": {
    "ico": 3,
    "txt": 31,
    "jpg": 97,
    "png": 385,
    "pdf": 10,
    "jpeg": 98,
    "svg": 11
  },
  "https://afcwebsite.blob.core.usgovcloudapi.net": {
    "ico": 17,
    "txt": 115,
    "jpg": 424,
    "png": 1531,
    "png&quot": 5,
    "pdf": 17,
    "jpeg": 501,
    "jpg&quot": 20,
    "svg": 62
  },
  "https://age.blob.core.usgovcloudapi.net": {
    "17": 1,
    "pdf": 2
  },
  "http://age.blob.core.usgovcloudapi.net": {
    "17": 1,
    "pdf": 2
  },
  "https://arxalertprod.blob.core.usgovcloudapi.net": {
    "ico": 3,
    "jpeg?se=2023-08-19t10%3a40%3a03z&sp=r&sv=2021-12-02&sr=b&sig=dus4lrs0hxl5ng6xzil2xrjwetc4ygrgy1dhwqzsqlo%3d": 1,
    "jpg": 3,
    "jpg?se=2023-01-10t18%3a03%3a14z&sp=r&sv=2021-08-06&sr=b&sig=lixvf6wmuuvphsticiwfdwb4sxvv7aaaho8whcyx%2b1y%3d": 1,
    "jpg?se=2023-06-05t01%3a12%3a57z&sp=r&sv=2021-12-02&sr=b&sig=h2dkfoonqw3swp%2bnbnde%2bra45oaf/8woalvldbrucak%3d": 1,
    "png?se=2022-12-11t19%3a35%3a31z&sp=r&sv=2021-08-06&sr=b&sig=i%2bes8ijeyk8g4gekpakbzn%2b/4uqmkuvwjk3bkd4i1v8%3d": 1,
    "jpeg": 1,
    "png": 52,
    "png?se=2022-05-11t10%3a40%3a06z&sp=r&sv=2021-04-10&sr=b&sig=1qdtytt3nq1r5d3mgi4qq9/lfn2nvw%2bmmgg09%2bochqk%3d": 1,
    "bmp": 1,
    "png?se=2022-12-28t10%3a16%3a49z&sp=r&sv=2021-08-06&sr=b&sig=dkdkvdnv%2b24uxps7td8brrmgvjvwxkkvnivlbnihhwo%3d": 1,
    "jpeg?se=2023-01-23t13%3a13%3a38z&sp=r&sv=2021-08-06&sr=b&sig=cqejx8pqbmwwktlrqc0qc7ewtpgd3iwvc2abpn8frya%3d": 1,
    "jpg?se=2022-12-10t05%3a38%3a59z&sp=r&sv=2021-08-06&sr=b&sig=nzyogp1vvk0ga8tpncbsxbr8q%2bfeiem0vaza3ew8qeq%3d": 1,
    "txt": 31,
    "otf": 36,
    "svg": 4,
    "css": 58,
    "js": 48,
    "pdf": 10
  },
  "https://atlasmaintenance.blob.core.usgovcloudapi.net": {
    "html": 1,
    "png": 1
  },
  "http://ausgvqmprov.blob.core.usgovcloudapi.net": {
    "txt": 1
  },
  "https://bangkok.blob.core.usgovcloudapi.net": {
    "ico": 3,
    "jpg?v=636769902040000000": 4,
    "jpg?v=636771491580000000": 4,
    "jpg?v=636771491310000000": 4,
    "png": 24,
    "jpg": 341,
    "jpeg": 1,
    "txt": 20
  },
  "https://budapest.blob.core.usgovcloudapi.net": {
    "ico": 2,
    "jpg": 351,
    "png": 156,
    "jpeg": 35,
    "txt": 15
  },
  "https://caccape.blob.core.usgovcloudapi.net": {
    "txt": 1,
    "jpg": 1
  },
  "https://caccapl.blob.core.usgovcloudapi.net": {
    "ico": 7,
    "txt": 23,
    "pdf": 135,
    "png": 3,
    "pptx": 1,
    "net/web/repository/army-modernization-": 1,
    "jpg": 7
  },
  "http://caplalaca-plpfwstorprod01.blob.core.usgovcloudapi.net": {
    "net/": 1,
    "js": 1
  },
  "http://caplalacaplpfwstor-prod01.blob.core.usgovcloudapi.net": {
    "pdfto": 1
  },
  "https://caplalacaplpfwstorprod01.blob.core.usgovcloudapi.net": {
    "ico": 3,
    "txt": 11,
    "jpg": 38,
    "png": 62,
    "mp4": 2,
    "pdf": 304,
    "pptx": 13,
    "docx": 2,
    "docx-": 1,
    "net/web/repository/pdf-": 1
  },
  "https://cboeprod.blob.core.usgovcloudapi.net": {
    "ico": 2,
    "png": 49,
    "pdf": 81,
    "jpg": 1,
    "jpg?itok=xkhhso4q": 62,
    "png?itok=xvybejlr": 42,
    "png?itok=ddylxyrk": 42,
    "png?itok=coo8t2vf": 42,
    "png?itok=nb-j6h4i": 12,
    "png?itok=9arrejwl": 30,
    "png?itok=hwmos7gd": 3,
    "png?itok=4ey7ss5r": 42,
    "png?itok=fsw0w-sd": 39,
    "png?itok=baeleibl": 12,
    "png?itok=2pxal0vf": 30,
    "txt": 26
  },
  "https://cboeresults.blob.core.usgovcloudapi.net": {
    "pdf": 1
  },
  "https://ccaidev.blob.core.usgovcloudapi.net": {
    "js": 1
  },
  "https://ccgappstorage.blob.core.usgovcloudapi.net": {
    "pdf": 2
  },
  "https://cemmlibrarystorage.blob.core.usgovcloudapi.net": {
    "jpg": 1,
    "ico": 1,
    "txt": 3
  },
  "https://cemmorgstorage2.blob.core.usgovcloudapi.net": {
    "jpg": 1
  },
  "https://ceproviderstorage.blob.core.usgovcloudapi.net": {
    "pdf": 7,
    "xlsx": 1,
    "txt": 2
  },
  "http://ceproviderstorage.blob.core.usgovcloudapi.net": {
    "pdf": 2
  },
  "https://ceproviderstorageaz.blob.core.usgovcloudapi.net": {
    "pdf": 1
  },
  "https://chicagopolicepublic.blob.core.usgovcloudapi.net": {
    "pdf": 68,
    "html": 23,
    "ico": 14,
    "g64x": 3,
    "mp4": 16,
    "mp4?fbclid=iwar0ce3vrs3vhjjxkhqykfpcpmemykzb5twheaijmjxppjivkaw_3fwnuu_e": 1,
    "mp4?fbclid=iwar15wjr_al_nuhuvykpqhgsh5njk3nn98wua6xes7inax3aogqgsiweq0ca": 1,
    "mp4?fbclid=iwar17qznfvkk-lcoquezrahyotasuz-ie70xidmnsdhc-sswk3rvvxx3cfyk": 1,
    "mp4?fbclid=iwar2o3xekqasluejynjeewjkm0nkyfssdpzbmacrndhrnabz298kmyp-zmdo": 1,
    "mp4?fbclid=iwar2rmq-lc775ejijv3xtqs9upfe5aswyeydhc7hqkiub6qp6rnfg1tzails": 1,
    "mp4?fbclid=iwar30jc_b0ocwk34xmki7j2hrdgn0beep3tdknzgutd4my0y34o8nzueifhg": 1,
    "mp4?fbclid=iwar32dxebz_wmj0ysxgzvhguzjg5gtqmbi3soyexiwtwlggq2of7currlwug": 1,
    "mp4?fbclid=iwar3_bbyo47dr2z1saoinduxbnwfxcnmrdwrudx4ecjikopkwtrhufmiifoo": 1,
    "mp4?fbclid=iwar3jilkbwumeizilgdfkqyuf67uiowtyg15f6d_8dqloslvw8ea7jlnhvve": 1,
    "mp4fbclid=iwar3_bbyo47dr2z1saoinduxbnwfxcnmrdwrudx4ecjikopkwtrhufmiifoo": 1,
    "net/ois-je184865-5200-s-eddy/": 1,
    "txt": 20,
    "net/smollett/": 1,
    "%20park%20dr/original%20": 2,
    "xml": 6,
    "net/smollett/smollett%20batch%2020%20-%20lineup%20": 2,
    "net/smollett/smollett%20batch%2021%20-%20photo%20": 2,
    "net/videos-and-documents-19sw5247/": 3,
    "html?fbclid=iwar37xgothdpegipo9ohrdfz1py5fwdj3qpojpxwcqrotydyeksn6x8-kzjy": 1
  },
  "https://cityofraleigh0drupal.blob.core.usgovcloudapi.net": {
    "net/": 11,
    "net/drupal": 1,
    "zip": 305,
    "pdf": 913494,
    "doc": 28,
    "net/drupal-prod/cor10/historic%20context%20": 1,
    "com": 2,
    "net/drupal-prod/cor12/indoor-face-covering-proclama-": 1,
    "01%20ral&utm_term=raltoday%20subscribers%20-%20master": 1,
    "docx": 19,
    "net/drupal-prod/cor13/we": 2,
    "pdf%22": 6,
    "pdf%22,": 8,
    "net/drupal-prod/cor14/council-group-study-": 2,
    "xlsx": 10,
    "pdf?fbclid=iwar2nfufeys_5r1b6nktdb1zq7zss4yy_yjru5rydojou3kk8bgjnf-xwqoa": 1,
    "net/drupal-prod/cor14/emerge": 1,
    "pdf?fbclid=iwar0psblh3yntbwzy3_vy6zlej5gwhzvyhlgrj1sxmjsgwqfnkw1s32mmtiw&mibextid=zxz2cz": 1,
    "pdf?mibextid=zxz2cz": 1,
    "xls": 1,
    "dgn": 517,
    "dwg": 227,
    "pdff": 1,
    "pdf17": 1,
    "pdf18": 1,
    "07%20ral&utm_term=raltoday%20subscribers%20-%20master": 3,
    "12%20ral&utm_term=raltoday%20subscribers%20-%20master": 1,
    "jpg": 626,
    "pdf?fbclid=iwar00fdsolz6t3rye4sq2e8bbzf8qgurylptlumi5c-geghuigywutndc1jg": 2,
    "net/drupal-prod/cor22/cpusection03land": 1,
    "pptx": 5,
    "05%20ral&utm_term=raltoday%20subscribers%20-%20master": 1,
    "png": 87,
    "pdfsan": 1,
    "net/drupal-prod/cor23/bodyw": 1,
    "net/drupal-prod/cor24/": 1,
    "21%20ral&utm_term=raltoday%20subscribers%20-%20master": 1,
    "30%20ral&utm_term=raltoday%20subscribers%20-%20master": 1,
    "pdf?sourceid=1028643&emci=12a5191c-70e5-eb11-a7ad-501ac57b8fa7&emdi=7f759ba5-41e6-eb11-a7ad-501ac57b8fa7&ceid=7097854": 1,
    "net/drupal-prod/cor24/fayettevillestreetdowntownraleighkiosksrfq": 1,
    "pdf)": 1,
    "03%20ral&utm_term=raltoday%20subscribers%20-%20master": 1,
    "net/drupal-prod/cor24/parkquarterlyusereport": 2,
    "net/drupal-prod/cor24/sip-": 1,
    "pdf(visited": 1,
    "net/drupal-prod/cor25/o": 1,
    "net/drupal-prod/cor28/goraleigh-public-particip": 1,
    "net/drupal-prod/cor28/members%20list_stakeholder%20committee%20meeting%20": 1,
    "xlsm": 2,
    "15%20ral&utm_term=raltoday%20subscribers%20-%20master": 1,
    "ico": 392,
    "txt": 1366
  },
  "http://cityofraleigh0drupal.blob.core.usgovcloudapi.net": {
    "pdf": 9,
    "txt": 9
  },
  "https://cjdtpublicstorageprod.blob.core.usgovcloudapi.net": {
    "zip": 1
  },
  "https://ckapfwstor001.blob.core.usgovcloudapi.net": {
    "pdf": 1995,
    "jpg": 796,
    "png": 131,
    "gif": 42,
    "net/achh/partiiiawards": 1,
    "ico": 13,
    "epub": 2,
    "mobi": 2,
    "net/pfw-images/dbimages/ameddc": 1,
    "css": 1,
    "pdf%22%20alt=%22ccc%20leadership%20development%22": 1,
    "pdf%22%20alt=%22department%20of%20nursing%20science%22": 1,
    "pdf%22%20alt=%22dmrti%20course%20offerings%22": 1,
    "pdf%22%20alt=%22dpmt%20course%20international%20brochure%22": 1,
    "svg": 6,
    "net/pfw-images/dbimages/how%20to%20complete%20pha%20part%201%20": 1,
    "pdf%22%20alt=%22international%20programs%20division%20brochure%22": 1,
    "pdf%22%20alt=%22jmesi%20course%20offerings%22": 1,
    "js": 7,
    "pdf%22%20alt=%22medical%20strategic%20leadership%20program%22": 1,
    "pdf%22%20alt=%22metc%20brochure%22": 1,
    "pdf%22%20alt=%22ncoa%20brochure%22": 1,
    "pdf%22%20alt=%22public%20health%20brochure%22": 1,
    "mp4": 2,
    "jpeg": 3,
    "pdf%22%20alt=%22public%20health%20courses%22": 1,
    "pdf%22%20alt=%22ipd%20programming%20guide%202019-2020%20%22": 1,
    "pdf%22%20alt=%22vetrinary%20brochure%22": 1,
    "txt": 99
  },
  "http://ckapfwstor001.blob.core.usgovcloudapi.net": {
    "js": 1,
    "net/pfw-images/dbimages/fund": 1
  },
  "http://clvfiles.blob.core.usgovcloudapi.net": {
    "net/": 1,
    "txt": 1
  },
  "https://clvfiles.blob.core.usgovcloudapi.net": {
    "jpg": 45,
    "ico": 6,
    "js": 12,
    "css?v=latest": 10,
    "txt": 25,
    "json": 5
  },
  "https://clvfilesdev.blob.core.usgovcloudapi.net": {
    "ico": 2,
    "txt": 5,
    "gif": 4,
    "gif%e2%80%99": 1
  },
  "https://complaints.blob.core.usgovcloudapi.net": {
    "pdf": 5,
    "txt": 1
  },
  "https://crexternal.blob.core.usgovcloudapi.net": {
    "ico": 3,
    "txt": 8,
    "net/smolett/": 1,
    "html": 5,
    "pdf": 11,
    "pdf%20": 1
  },
  "https://devcorrpublicdatahub.blob.core.usgovcloudapi.net": {
    "json": 2
  },
  "http://docpodcast.blob.core.usgovcloudapi.net": {
    "net/": 1,
    "txt": 1
  },
  "https://docpodcast.blob.core.usgovcloudapi.net": {
    "ico": 5,
    "mp3?_=1": 16,
    "mp3?_=2": 8,
    "mp3?_=5": 2,
    "mp3?_=4": 2,
    "mp3": 27,
    "mp3?_=8": 1,
    "mp3?_=9": 1,
    "mp3?_=3": 2,
    "mp3?_=6": 1,
    "mp3?_=7": 1,
    "txt": 39
  },
  "https://dotcomstorage.blob.core.usgovcloudapi.net": {
    "jpg": 3,
    "pdf": 1
  },
  "https://dphcontent.blob.core.usgovcloudapi.net": {
    "jpg": 3
  },
  "http://durhamcompass.blob.core.usgovcloudapi.net": {
    "txt": 1
  },
  "https://eddsa.blob.core.usgovcloudapi.net": {
    "30%20(updated": 2,
    "pdf": 166,
    "pdf?sp=r&st=2020-12-30t17:22:17z&se=2024-04-01t04:00:00z&spr=https&sv=2019-10-10&sr=b&sig=eqcbyloylueurixgtaq99%2bui5tj6p09lmg7m8idpchm%3d": 2,
    "pdf?se=2024-04-01t04%3a00%3a00z&sig=eqcbyloylueurixgtaq99%2bui5tj6p09lmg7m8idpchm%3d&sp=r&spr=https&sr=b&st=2020-12-30t17%3a22%3a17z&sv=2019-10-10": 1,
    "mp4?sp=r&st=2022-01-04t18:54:54z&se=2032-01-05t02:54:54z&spr=https&sv=2020-08-04&sr=b&sig=1nkbg4qttdzv1bhpqwnoy7qmdqfzaz8zjnlmz%2fevaia%3d": 1,
    "pdf?sp=r&st=2021-10-21t17:13:18z&se=2029-10-22t01:13:18z&spr=https&sv=2020-02-10&sr=b&sig=e8dpqzcgbuep4whvoavzrdphld2nrocsc3nxhz2owni%3d": 3,
    "pdf?sp=r&st=2021-10-21t17%3a13%3a18z&se=2029-10-22t01%3a13%3a18z&spr=https&sv=2020-02-10&sr=b&sig=e8dpqzcgbuep4whvoavzrdphld2nrocsc3nxhz2owni%3d": 1,
    "ico": 18,
    "net/public/": 1,
    "net/public/650033_2023_noelle_dunphy_v_rudolph_w_giuliani_et_al_complaint_10": 1,
    "pdf?fbclid=iwar0s_hvismhrhfa3jkfb79djiqe3snasvrzfknqr3yeroihqyvwkmpnhp7e": 3,
    "pdf?fbclid=iwar1kasye0ozh7mzxvls9axnrbczmvi8lvqx4lepxokezeaj3kpwosedgfgk": 1,
    "pdf?fbclid=iwar1ynpoaeglvl0msqi9xivshj0lflqjedv6ujwqq1a7umxeieoxkciocdqi&mibextid=zxz2cz": 1,
    "pdf?fbclid=iwar2izxmi67w3lhhufo4c0um-t179lqxjyufdkd4ushvkcsuflwz04rhzhyc": 2,
    "pdf?fbclid=iwar3uvlgbu-oyztlu5szv8nekxettzj7sraeeqew65jbz_87d73bjlxuz6-g": 1,
    "pdf?mibextid=zxz2cz": 3,
    "pdf?utm_source=sailthru&utm_medium=newsletter&utm_campaign=daily-docket&utm_term=051623": 1,
    "pdf?utm_source=sailthru&utm_medium=newsletter&utm_campaign=daily-docket&utm_term=052023": 1,
    "pdf?utm_source=substack&utm_medium=email": 1,
    "net/public/85163_": 1,
    "net/public/85163_2022_george_gar-": 1,
    "pdf&ved=2ahukewiojybm_tr7ahviiiskhdklcqqqfnoeca8qaq&usg=aovvaw1waqmqfc2icfwl0bwulwft": 1,
    "pdf?bcs-agent-scanner=5c99e9ba-3822-444d-9c95-c394e08db44b": 2,
    "pdf?fbclid=iwar14bzelxathrc1aghyvihhbwsnbbs8_4o5st6qq1mvlml0bh7-uxmaei9e": 1,
    "pdf?fbclid=iwar1ymt9cjtraeks0ryrqxeif7eaz7isxd254o_smwxfsrdpvsgsi9rij_ps": 1,
    "pdf?fbclid=iwar2tjjli6yqlapxlhycivxy3zdzpm9qzbclgzq4jxv6nrketjbqigydtbma": 1,
    "pdf?fbclid=iwar37zmyde_wqbctydqvid17txaazlkvrvnr_vgt8deukqqzrtyiq4l6plla": 2,
    "pdf?utm_source=sendfox&utm_medium=email&utm_campaign=wcrc-update-103122": 1,
    "txt": 66
  },
  "https://ehydrotest.blob.core.usgovcloudapi.net": {
    "pdf": 1,
    "pdfcontinuing": 1
  },
  "https://esmsstorage.blob.core.usgovcloudapi.net": {
    "pdf": 1
  },
  "https://fagovopendata.blob.core.usgovcloudapi.net": {
    "xml": 1
  },
  "https://filedrop.blob.core.usgovcloudapi.net": {
    "docx": 1
  },
  "http://fnweb.blob.core.usgovcloudapi.net": {
    "net/": 3,
    "txt": 5
  },
  "https://fnweb.blob.core.usgovcloudapi.net": {
    "xml": 5,
    "ico": 6,
    "css": 8,
    "html": 4,
    "txt": 24,
    "js?owa3mq": 2,
    "js": 8,
    "js?ov5gf5": 1,
    "js?ovmbzt": 2,
    "js?oxbidw": 1,
    "js?oy16q9": 1,
    "js?ozkkur": 1,
    "js?p08upj": 4,
    "js?p1a4va": 1,
    "js?p1dqes": 1,
    "js?p1e6ti": 1,
    "js?p1ln04": 1,
    "js?p1p9n0": 1,
    "js?p1xo54": 1,
    "js?p1xy5c": 1,
    "js?p1y19p": 1,
    "js?p4merv": 1,
    "js?p56tbx": 1,
    "js?pekwn2": 1,
    "js?pfmbwj": 1,
    "htc": 2
  },
  "https://foia.blob.core.usgovcloudapi.net": {
    "ico": 1,
    "txt": 3,
    "png?sv=2021-06-08&se=2223-12-31t00%3a00%3a00z&sr=b&sp=r&sig=xfe%2bnwnoifoehpickz8mh5le9y1ccuhqmjrwwwlwsjm%3d": 1,
    "png?sv=2021-06-08&se=2223-12-31t00%3a00%3a00z&sr=b&sp=r&sig=wqrjplqjvu3j44yo0v8d7nis19uhhskyey86tzumgj4%3d": 1,
    "png?sv=2021-06-08&se=2223-12-31t00%3a00%3a00z&sr=b&sp=r&sig=ymghn6ivfl332tvvit%2fl%2bytpbuumux7%2ftfftso2ilcw%3d": 1,
    "jpg?sv=2021-06-08&se=2223-12-31t00%3a00%3a00z&sr=b&sp=r&sig=8ez716wkwcpbvsee9wuzxjzg19fhj7lppi9fep93bui%3d": 1
  },
  "https://g1configmanagement.blob.core.usgovcloudapi.net": {
    "txt": 1,
    "csv": 1
  },
  "https://g1modernizationsaa.blob.core.usgovcloudapi.net": {
    "htm": 1
  },
  "https://gaborone.blob.core.usgovcloudapi.net": {
    "ico": 1,
    "jpg?v=636915995890000000": 4,
    "jpg?v=636915996080000000": 4,
    "jpg?v=636915996110000000": 4,
    "jpg?v=636915996070000000": 4,
    "jpg?v=636765938740000000": 4,
    "jpg?v=636765938750000000": 4,
    "jpg": 71,
    "jpeg": 6,
    "txt": 8
  },
  "https://gccsummaryabatementblob.blob.core.usgovcloudapi.net": {
    "ico": 1,
    "txt": 1,
    "xml": 1,
    "net/summaryabatement/18%252": 1
  },
  "http://gccsummaryabatementblob.blob.core.usgovcloudapi.net": {
    "net/summaryabatement/18%252": 1
  },
  "http://govprod.blob.core.usgovcloudapi.net": {
    "js": 1,
    "net/twocms/": 1
  },
  "https://iacwppubliccontent.blob.core.usgovcloudapi.net": {
    "txt": 3,
    "png": 8
  },
  "https://ic3pdfs.blob.core.usgovcloudapi.net": {
    "pdf": 2,
    "txt": 1
  },
  "https://illinoistreasurergovprod.blob.core.usgovcloudapi.net": {
    "11": 1,
    "2017": 2,
    "2019": 4,
    "2020": 9,
    "2021": 4,
    "2022": 1,
    "ico": 58,
    "txt": 813,
    "net/twocms/": 1,
    "net/twocms/media/": 1,
    "net/twocms/media/doc/": 1,
    "pdf": 9395,
    "net/twocms/media/doc/2016": 1,
    "net/twocms/media/doc/2019-": 1,
    "xlsx": 32,
    "net/twocms/media/doc/ac": 1,
    "net/twocms/media/doc/accepta": 1,
    "net/twocms/media/doc/acceptable": 1,
    "pdf15": 1,
    "xls": 6,
    "net/twocms/media/doc/bankingservicesappendixe-": 1,
    "pdf;11": 1,
    "25%20(003": 1,
    "net/twocms/media/doc/examples": 2,
    "net/twocms/media/doc/formatted": 1,
    "docx": 4,
    "net/twocms/media/doc/il": 1,
    "net/twocms/media/doc/il%20": 1,
    "net/twocms/media/doc/il%20trea": 2,
    "net/twocms/media/doc/il%20treasurer%20white%20paper": 1,
    "net/twocms/media/doc/il%20treasurer%20white%20paper%20-": 1,
    "net/twocms/media/doc/il%20treasurer%20white%20paper%20-%20the%20investment%20case%20for%20": 1,
    "net/twocms/media/doc/il%20treasurer%20white%20paper%20-%20the%20investment%20case%20for%20board%20diversity%20(oct%202020": 1,
    "net/twocms/media/doc/il%20treasurer%20white%20paper%20-%20the%25": 1,
    "net/twocms/media/doc/il%20treasurer%20white%25": 2,
    "net/twocms/media/doc/il%20treasurer%20white%25-": 2,
    "net/twocms/media/doc/il%20treasurer%252": 1,
    "pdf?mc_cid=c7adb994ac&mc_eid=[d1b585bfce]": 1,
    "pdf?_cldee=yi5i7t5hrtzacicgahdodegmv89gcdqsx5hlfhknm4p6ajfn0moxupra2q9phrg-&recipientid=contact-5645bba28fe2ec11bb3d000d3a5a2a21-837f2111e4ca4f0d9c36c5e96328535d&esid=b7436517-4bce-ed11-b597-000d3a3148fb": 1,
    "pdf?fbclid=iwar0woni3t-fndjiwbw9lthvgashbuxfm_e0foixwedh8dntbdwohkx4zxpa": 2,
    "net/twocms/media/doc/midwest%20inve": 1,
    "net/twocms/media/doc/new%20long-termism%20rulemaking%20petition%20-%20esg%20disclosure%20(2018": 1,
    "pdf?fbclid=iwar3_gxzstmoosyb757jjvpi74ys4vey2l1lkugddafblemve4_12sokbmf4": 1,
    "net/twocms/media/doc/october2": 2,
    "net/twocms/media/doc/october2020_russ": 1,
    "net/twocms/media/doc/october2020_russe": 1,
    "net/twocms/media/doc/october2020_russell30": 1,
    "125see": 1,
    "132see": 1,
    "net/twocms/media/doc/report%20-": 2,
    "%20companies%20(august%202018": 1,
    "net/twocms/media/doc/report%20--": 1,
    "%20companies%20(october%202018": 2,
    "pdf28": 2,
    "net/twocms/media/doc/secure": 1,
    "net/twocms/media/doc/secure%20choice%20monthly%20dashboard_": 1,
    "pdf?fbclid=iwar1nxvgw_8khpajo9sjisbqd9wwwm7tkc5cxxnxcby4nnxeklbdqqhlximm": 2,
    "net/twocms/media/doc/state%20i": 1,
    "net/twocms/media/doc/sto%20-%202021%20proxy": 1,
    "net/twocms/media/doc/treasurer": 1,
    "xlsx?web=1": 1,
    "jpg": 1356,
    "png": 944,
    "jpeg": 41,
    "gif": 4
  },
  "https://illinoistreasurergovprod-secondary.blob.core.usgovcloudapi.net": {
    "txt": 2,
    "pdf": 5
  },
  "http://indianaenr.blob.core.usgovcloudapi.net": {
    "0": 4,
    "net/": 1,
    "ico": 3,
    "txt": 14,
    "net/site/": 2,
    "css": 23,
    "png": 4,
    "html": 5,
    "eot": 2,
    "svg": 2,
    "ttf": 2,
    "woff": 2,
    "woff2": 2,
    "js": 130
  },
  "https://indianaenr.blob.core.usgovcloudapi.net": {
    "0": 41,
    "net/archive/2016general/": 1,
    "json": 84,
    "css": 368,
    "png": 70,
    "html": 186,
    "eot": 19,
    "svg": 19,
    "ttf": 19,
    "woff": 19,
    "woff2": 19,
    "js": 1770,
    "net/archive/2018general/%7b%7belectionresultsdocument%7d%7d": 1,
    "html%23": 1,
    "ico": 30,
    "txt": 103,
    "net/site/": 3,
    "htm": 1,
    "html?istopbanner=y": 10,
    "net/site/%7b%7belectionresultsdocument%7d%7d": 1,
    "xml": 3
  },
  "http://indianaenr.blob.core.usgovcloudapi.net:80": {
    "txt": 30
  },
  "http://inoistreasurergovprod.blob.core.usgovcloudapi.net": {
    "net/": 1
  },
  "https://jfcool4attachments.blob.core.usgovcloudapi.net": {
    "docx": 2,
    "pdf?sv=2020-08-04&st=2023-12-14t00%3a52%3a01z&se=2023-12-15t01%3a07%3a01z&sr=b&sp=r&sig=kubf8qpba%2fwivvvpn9xb53g1%2f292z83otqq64ig90su%3d": 1,
    "pdf?sv=2020-08-04&st=2023-12-14t00%3a52%3a01z&se=2023-12-15t01%3a07%3a01z&sr=b&sp=r&sig=zutlpffjdlcz3bnfqd7olnus8gnuvkdmifgll9syrxa%3d": 1,
    "pdf?sv=2020-08-04&st=2023-12-14t00%3a52%3a01z&se=2023-12-15t01%3a07%3a01z&sr=b&sp=r&sig=qhgni2shwa3cw0rf%2bdp%2f3gz%2fbmxfoe7tpggr%2fvvrq%2b0%3d": 1,
    "pdf": 2,
    "pdf?sv=2020-08-04&st=2023-12-14t00%3a52%3a02z&se=2023-12-15t01%3a07%3a02z&sr=b&sp=r&sig=57%2fmm6rc2y3gvz3ncskr4j%2fyuquovyu%2f0qpi94h22lg%3d": 1,
    "pdf?sv=2020-08-04&st=2023-12-14t00%3a52%3a03z&se=2023-12-15t01%3a07%3a03z&sr=b&sp=r&sig=iddwkkoplsddymwmdqk%2bg1ti0k2how0fqefx%2bmmqpqi%3d": 1,
    "pdf?sv=2020-08-04&st=2022-03-19t02%3a21%3a43z&se=2022-03-20t02%3a26%3a43z&sr=b&sp=r&sig=yu1%2fptt68cvvxwqg4tku3ciadl7nuon4tukvv5zizbs%3d": 1,
    "pdf?sv=2020-08-04&st=2022-03-19t02%3a24%3a01z&se=2022-03-20t02%3a29%3a01z&sr=b&sp=r&sig=tkj%2fzwa4e7tpuka%2fbzkcqgr9vps9geccw5iv7eclyvy%3d": 1,
    "pdf?sv=2020-08-04&st=2022-03-22t15%3a13%3a02z&se=2022-03-23t15%3a18%3a02z&sr=b&sp=r&sig=vgfju3b2w6wpcht9mguax2owrom9%2falz8cogjbicdsc%3d": 1,
    "pdf?sv=2020-08-04&st=2022-03-19t02%3a33%3a10z&se=2022-03-20t02%3a38%3a10z&sr=b&sp=r&sig=pjftu5tefddiy95ixtchz%2b3zekeakkvnby9fr2hbkjo%3d": 1,
    "pdf?sv=2020-08-04&st=2022-03-22t15%3a12%3a25z&se=2022-03-23t15%3a17%3a25z&sr=b&sp=r&sig=u6zarfd8bsx9xefirkgut5dg%2bds4lrucfmlhus6xrdm%3d": 1,
    "pdf?sv=2018-03-28&sr=b&sig=py21hcqvwdqjmcwidxkk9htncipdyxqhluqkhx1fvb0%3d&st=2020-11-16t07%3a14%3a12z&se=2020-11-17t07%3a19%3a12z&sp=r": 1,
    "pdf?sv=2020-04-08&st=2021-08-10t20%3a54%3a44z&se=2021-08-11t20%3a59%3a44z&sr=b&sp=r&sig=beled57sak%2fthphlr3rbr7h112r9rpj76a%2b%2fwnk6tyi%3d": 1,
    "pdf?se=2024-01-04t21%3a19%3a46z&sig=pmvenqoc11vlifbtv%2fz60jjqjgtuf1qucuxh2gmcxew%3d&sp=r&sr=b&st=2024-01-03t21%3a04%3a46z&sv=2020-08-04": 1,
    "pdf?se=2023-12-31t16%3a10%3a02z&sig=qcyh6%2bnkhtf08ejeyvhzt1sresjcxhncldeagonlvmm%3d&sp=r&sr=b&st=2023-12-30t15%3a55%3a02z&sv=2020-08-04": 1,
    "pdf?sv=2018-03-28&sr=b&sig=cdbgpfbo%2bjq5ufmw%2bauxcmqctmz2mhh1k7xmxcf%2bjgi%3d&st=2020-11-16t07%3a14%3a14z&se=2020-11-17t07%3a19%3a14z&sp=r": 1,
    "pdf?sv=2018-03-28&sr=b&sig=itrublwcwgy1a8takq7hl0mzmk6d7mqtg4wrksbzhrc%3d&st=2020-11-16t07%3a14%3a16z&se=2020-11-17t07%3a19%3a16z&sp=r": 1,
    "pdf?sv=2018-03-28&sr=b&sig=yadxidnpd5c31ao9hjrp0myc%2b1ihvudbai7gewtfcc4%3d&st=2020-11-16t07%3a14%3a06z&se=2020-11-17t07%3a19%3a06z&sp=r": 1,
    "pdf?sv=2018-03-28&sr=b&sig=yibiaqstserbjgint65dkl8bzhkinx%2fgaso9jtijhf4%3d&st=2020-11-16t07%3a14%3a13z&se=2020-11-17t07%3a19%3a13z&sp=r": 1,
    "pdf?sv=2018-03-28&sr=b&sig=am2zrr0%2b%2bpzqmhcrchplcna009k4ij3ywiigbnsth04%3d&st=2020-11-16t07%3a14%3a08z&se=2020-11-17t07%3a19%3a08z&sp=r": 1,
    "txt": 4
  },
  "http://joelorchstorage.blob.core.usgovcloudapi.net": {
    "txt": 1
  },
  "https://ktoletsencrypt.blob.core.usgovcloudapi.net": {
    "net/public/": 5
  },
  "https://landingpageblod.blob.core.usgovcloudapi.net": {
    "ico": 1,
    "png": 1
  },
  "https://lapdonlinestrgeacc.blob.core.usgovcloudapi.net": {
    "ico": 120,
    "pdf": 2097,
    "jpg": 12314,
    "svg": 20848,
    "png": 3281,
    "jpeg": 59,
    "pdf,accessedaugust": 1,
    "pdf%22": 1,
    "p": 1,
    "gif": 122,
    ")": 1,
    "net/lapdonlinemedia/2021/11/csp-evaluation-": 1,
    "net/lapdonlinemedia/2021/12/strategic-plan-": 1,
    "net/lapdonlinemedia/2021/12/strategic-plan-2021-to-": 1,
    "net/lapdonlinemedia/2022/01/2019_uof_year-": 1,
    "net/lapdonlinemedia/2022/03/3_9_22_so_no": 2,
    "_3_poli": 1,
    "_3_policy_limita": 1,
    "_3_policy_limitati": 1,
    "net/lapdonlinemedia/2022/09/senior_crime_prevention": 1,
    "txt": 225
  },
  "https://lawmakerdocuments.blob.core.usgovcloudapi.net": {
    "net/": 110,
    "ico": 1,
    "jpg": 109,
    "webp": 387,
    "png": 92,
    "txt": 111
  },
  "https://mcclibrary.blob.core.usgovcloudapi.net": {
    "net/codecontent/": 3,
    "png": 526,
    "pdf": 17,
    "ico": 2,
    "txt": 5
  },
  "https://mccmeetings.blob.core.usgovcloudapi.net": {
    "pdf": 2818,
    "css": 26,
    "ico": 2,
    "net/losaltosca-": 1,
    "net/palmerlake-pubu/meet-packet-a147a276f-": 1,
    "txt": 80,
    "net/sheboygnwi-pubu/meet-packet-59c9340e237": 1
  },
  "https://mccmeetingspublic.blob.core.usgovcloudapi.net": {
    "pdf": 2920,
    "net/beaumntca-meet-f1da32f813d04b548d03815d09f7fef6/item-attachment-004-": 1,
    "png": 11,
    "jpg": 6,
    "pdf?goal=0_c2357fd0a3-dc0dda75ef-84421887": 1,
    "pdf?utm_source=voice+of+san+diego+master+list&utm_campaign=dc0dda75ef-morning_report&utm_medium=email&utm_term=0_c2357fd0a3-dc0dda75ef-84421887&goal=0_c2357fd0a3-dc0dda75ef-84421887": 1,
    "txt": 63
  },
  "https://mccmeetingsresources.blob.core.usgovcloudapi.net": {
    "png": 3,
    "svg": 5,
    "ico": 3,
    "css": 3,
    "woff": 2,
    "css?ver=1cf15ba5-9e9d-4f95-827c-745953bb2d6a": 1,
    "css?ver=7c420161-25df-4bbb-837b-d0af72f8733c": 1,
    "css?ver=e191faa8-4c7d-4103-b8be-6639c11ff59b": 1,
    "txt": 7
  },
  "https://mcoecbamcoepwprd01.blob.core.usgovcloudapi.net": {
    "8": 1,
    "9": 1,
    "ico": 2,
    "pdf": 36,
    "net/library/cava": 1,
    "net/library/cavalryar": 1,
    "net/library/ebooks/assessment_of_men_": 1,
    "txt": 8
  },
  "https://medcoeckapwstorprd01.blob.core.usgovcloudapi.net": {
    "pdf": 289,
    "jpg": 117,
    "net/achh/amedd_history_newsletter": 1,
    "png": 6,
    "docx": 2,
    "gif": 13,
    "epub": 15,
    "mobi": 2,
    "pdf%e2%80%99": 1,
    "jfif": 4,
    "net/pfw-images/dbimages/medicalconseqnuclear": 1,
    "txt": 21
  },
  "https://ndiastorage.blob.core.usgovcloudapi.net": {
    "4": 1,
    "175": 1,
    "ico": 2,
    "pdf": 15666,
    "net/ndia/200": 1,
    "pdf%20-%20create,%20discover%20and%20share%20awesome%20gifs%20on%20gfycat": 1,
    "pdf%20gif": 1,
    "ppt": 1115,
    "net/ndia/2003/systems/": 1,
    "pdf)": 2,
    "doc": 15,
    "net/ndia/2004/cmmi/cmmit1wedam/1295sandyshrum": 1,
    "pps": 6,
    "net/ndia/2004/test/mon": 1,
    "net/ndia/2004/test/thurs": 1,
    "net/ndia/2004/test/tues": 1,
    "net/ndia/2004/test/wed": 1,
    "net/ndia/2006/systems/wednesday/": 1,
    "pdf,2006": 1,
    "net/ndia/2007/": 1,
    "net/ndia/2007/psa_": 1,
    "pdf%ef%bc%bb": 1,
    "pdf%ef%bc%bb23%ef%bc%bd": 1,
    "net/ndia/2008/psa_apr/": 1,
    "net/ndia/2009/systemengr/": 1,
    "[29": 1,
    "net/ndia/2010/targets/": 1,
    "pptx": 16,
    "net/ndia/2015/armament/": 1,
    "net/ndia/2016/": 1,
    "net/ndia/2016/human/s": 1,
    "p": 1,
    "net/ndia/2016/test/ot": 1,
    "net/ndia/2017/armament/bakertutoria": 1,
    "pdf%e2%80%a2": 1,
    "net/ndia/2017/power/potter19503pdf": 1,
    "net/ndia/2017/systems/wednesday/track1/19870_david": 1,
    "pdf[12": 1,
    "net/ndia/2018/": 1,
    "net/ndia/2022/systems/": 1,
    "txt": 17
  },
  "https://nysocadmzmedia.blob.core.usgovcloudapi.net": {
    "wmv": 1,
    "pdf": 2
  },
  "https://occprodstoragev1.blob.core.usgovcloudapi.net": {
    "ico": 2,
    "net/lsmatterattachmentspublic": 1,
    "pdf": 10612,
    "net/lsmatterattachmentspublic/4c89c8": 1,
    "net/lsmatterattachmentspublic/b6c99d86-fa": 1,
    "net/matterattachmentspub": 1,
    "net/matterattachmentspublic/66607fc5-83d": 1,
    "pdf%20": 1,
    "pdf%20)": 1,
    "pdf)": 1,
    "net/matterattachmentspublic/c818c624-7b": 1,
    "net/matterattachmentspublic/e844267c-3409-456a-8fd3-": 1,
    "net/matterattachmentspublic/f86589f4-55c8-4530-95a8-": 1,
    "docx": 7,
    "txt": 30
  },
  "https://ocprodocprodnamgs.blob.core.usgovcloudapi.net": {
    "js": 419,
    "gov&data-lcw-version=prod": 37,
    "css": 77,
    "json": 37,
    "gov&data-hide-chat-button=true&data-lcw-version=prod": 3,
    "svg": 100,
    "txt": 31
  },
  "https://ocscsastdb2c.blob.core.usgovcloudapi.net": {
    "html": 1
  },
  "https://omaopublicshare.blob.core.usgovcloudapi.net": {
    "pdf": 22
  },
  "https://podcast.blob.core.usgovcloudapi.net": {
    "xml": 767
  },
  "https://portalfiles.blob.core.usgovcloudapi.net": {
    "pdf": 1
  },
  "https://publicaccessstorage.blob.core.usgovcloudapi.net": {
    "pdf": 22,
    "docx": 17,
    "ppsx": 1,
    "xlsx": 7,
    "rtf": 1
  },
  "https://saocscstdpubwebnav.blob.core.usgovcloudapi.net": {
    "png": 12,
    "css": 20
  },
  "https://saocscstdpubwebnavdev.blob.core.usgovcloudapi.net": {
    "png": 1,
    "css": 2
  },
  "https://sapublicassets.blob.core.usgovcloudapi.net": {
    "jpg": 2
  },
  "https://staao.blob.core.usgovcloudapi.net": {
    "ico": 3,
    "js": 7,
    "jpg": 543,
    "png": 273,
    "svg": 8,
    "jpeg": 3,
    "net/images-products-content/high-density-centaur%20pcb": 1,
    "txt": 13
  },
  "https://stjececmsdusgva001.blob.core.usgovcloudapi.net": {
    "ico": 2,
    "pdf": 26,
    "webp": 45,
    "jpg": 15,
    "png": 38,
    "txt": 25
  },
  "https://storage.blob.core.usgovcloudapi.net": {
    "net/ndia/2018/": 1
  },
  "https://storageccec.blob.core.usgovcloudapi.net": {
    "ico": 1,
    "pdf": 13,
    "xlsx": 1,
    "txt": 2
  },
  "http://storageccec.blob.core.usgovcloudapi.net": {
    "net/public/docs/293-clean-elex-ed-ltr-to-": 1,
    "pdf": 2
  },
  "https://tradocccoeceaccoepfwp1.blob.core.usgovcloudapi.net": {
    "svg": 1,
    "png": 66,
    "txt": 3,
    "jpg": 8,
    "gif": 1
  },
  "https://tradocfcoeccafcoepfwprod.blob.core.usgovcloudapi.net": {
    "pdf": 27,
    "png": 27,
    "jpg": 28,
    "jpg?version=2": 2,
    "ico": 2,
    "net/fires-bulletin-archive/2003/sep_oct_2003/sep_oct_2003_": 1,
    "jfif": 10,
    "txt": 8,
    "pdf?version=2": 1
  },
  "https://vemspublic.blob.core.usgovcloudapi.net": {
    "mp4?sp=r&st=2023-11-13t15:25:06z&se=2024-01-01t23:25:06z&spr=https&sv=2022-11-02&sr=b&sig=5klieqc7ugla3gppughxgyxcb%2fala7adttd1kz4t5oo%3d": 1
  }
}
